cpar/__init__.py
cpar/char.py
cpar/digit.py
cpar-1.0.3.dist-info/LICENCE
cpar-1.0.3.dist-info/METADATA
cpar-1.0.3.dist-info/WHEEL
cpar-1.0.3.dist-info/top_level.txt
cpar-1.0.3.dist-info/RECORD
