Metadata-Version: 2.1
Name: cpar
Version: 1.0.3
Summary: This package contains CPAR dataset
Home-page: https://github.com/gaganmanku96/cpar
Author: Gagandeep Singh
Author-email: gaganmanku96@gmail.com
License: License :: OSI Approved :: MIT License
Platform: UNKNOWN
Classifier: Programming Language :: Python
Classifier: Programming Language :: Python :: 3
Classifier: Operating System :: OS Independent
Requires-Python: >=3.4
Requires-Dist: numpy
Requires-Dist: tqdm
